tile_operator/__init__.py
tile_operator/operate.py
tile_operator-0.0.6.dist-info/LICENSE
tile_operator-0.0.6.dist-info/WHEEL
tile_operator-0.0.6.dist-info/METADATA
tile_operator-0.0.6.dist-info/RECORD
