Metadata-Version: 2.1
Name: tile-operator
Version: 0.0.6
Summary: Tile Operation tool
Author: nokonoko1203
Author-email: nokonoko.1203.777@gmail.com
Requires-Python: >=3.8,<4.0
Classifier: Programming Language :: Python :: 3
Classifier: Programming Language :: Python :: 3.8
Classifier: Programming Language :: Python :: 3.9
Classifier: Programming Language :: Python :: 3.10
Classifier: Programming Language :: Python :: 3.11
Requires-Dist: click (>=8.1.0,<9.0.0)
Requires-Dist: geopandas (>=0.12.0,<0.13.0)
Requires-Dist: matplotlib (>=3.6.0,<4.0.0)
Requires-Dist: mercantile (>=1.2.0,<2.0.0)
Requires-Dist: numpy (>=1.23.0,<2.0.0)
Requires-Dist: pillow (>=9.3.0,<10.0.0)
Requires-Dist: rasterio (>=1.3.0,<2.0.0)
Requires-Dist: requests (>=2.28.0,<3.0.0)
Requires-Dist: tqdm (>=4.64.0,<5.0.0)
